pypakr/__init__.py
pypakr/pypakr.py
pypakr_pkg-0.0.4.data/scripts/pypakr
pypakr_pkg-0.0.4.dist-info/DESCRIPTION.rst
pypakr_pkg-0.0.4.dist-info/METADATA
pypakr_pkg-0.0.4.dist-info/RECORD
pypakr_pkg-0.0.4.dist-info/WHEEL
pypakr_pkg-0.0.4.dist-info/metadata.json
pypakr_pkg-0.0.4.dist-info/top_level.txt
