Metadata-Version: 2.0
Name: pypakr-pkg
Version: 0.0.4
Summary: Python containers
Home-page: https://github.com/ajanicij/pypakr
Author: Aleksandar Janicijevic
Author-email: aleks@vogonsoft.com
License: UNKNOWN
Platform: UNKNOWN
Classifier: Programming Language :: Python :: 2.7
Classifier: License :: OSI Approved :: Apache Software License
Classifier: Operating System :: POSIX :: Linux
Requires-Dist: vex
Requires-Dist: virtualenv (>=10.0.0)
